aio_bunny/__init__.py
aio_bunny/bunny.py
aio_bunny/consumer.py
aio_bunny/exchange_types.py
aio_bunny/version.py
aio_bunny-0.0.3.dist-info/LICENSE
aio_bunny-0.0.3.dist-info/METADATA
aio_bunny-0.0.3.dist-info/WHEEL
aio_bunny-0.0.3.dist-info/top_level.txt
aio_bunny-0.0.3.dist-info/RECORD
